clubs/__init__.py
clubs/configs.py
clubs/error.py
clubs/poker/__init__.py
clubs/poker/card.py
clubs/poker/engine.py
clubs/poker/evaluator.py
clubs/render/__init__.py
clubs/render/ascii_table.txt
clubs/render/ascii_viewer.py
clubs/render/graphic.py
clubs/render/viewer.py
clubs-0.1.4.dist-info/LICENSE
clubs-0.1.4.dist-info/METADATA
clubs-0.1.4.dist-info/WHEEL
clubs-0.1.4.dist-info/top_level.txt
clubs-0.1.4.dist-info/RECORD
